visionfi/__init__.py
visionfi/auth.py
visionfi/client.py
visionfi/exceptions.py
visionfi/utils.py
visionfi/visionfi_types.py
visionfi_client-2025.4.21.1.dist-info/licenses/LICENSE
visionfi_client-2025.4.21.1.dist-info/licenses/NOTICE.txt
visionfi_client-2025.4.21.1.dist-info/METADATA
visionfi_client-2025.4.21.1.dist-info/WHEEL
visionfi_client-2025.4.21.1.dist-info/top_level.txt
visionfi_client-2025.4.21.1.dist-info/RECORD
