Metadata-Version: 2.4
Name: visionfi-client
Version: 2025.4.21.1
Summary: Python client library for the VisionFi document analysis platform
Author: VisionFi Team
License: MIT License
Project-URL: Homepage, https://github.com/visionfi/visionfi-python
Project-URL: Bug Tracker, https://github.com/visionfi/visionfi-python/issues
Classifier: Programming Language :: Python :: 3
Classifier: Programming Language :: Python :: 3.7
Classifier: Programming Language :: Python :: 3.8
Classifier: Programming Language :: Python :: 3.9
Classifier: Programming Language :: Python :: 3.10
Classifier: License :: OSI Approved :: MIT License
Classifier: Operating System :: OS Independent
Requires-Python: >=3.7
License-File: LICENSE
License-File: NOTICE.txt
Requires-Dist: requests>=2.25.0
Requires-Dist: google-auth>=2.0.0
Requires-Dist: google-auth-oauthlib>=0.4.0
Requires-Dist: pydantic>=1.8.0
Dynamic: license-file
